{
  "project_info": {
    "project_number": "273465752756",
    "firebase_url": "https://fir-realtimedbcrud-62b14.firebaseio.com",
    "project_id": "fir-realtimedbcrud-62b14",
    "storage_bucket": "fir-realtimedbcrud-62b14.appspot.com"
  },
  "client": [
    {
      "client_info": {
        "mobilesdk_app_id": "1:273465752756:android:3999870cd8a546e5",
        "android_client_info": {
          "package_name": "com.asif047.firebaserealtimedbcrud"
        }
      },
      "oauth_client": [
        {
          "client_id": "273465752756-cmu9cq0k0sfu2i2vgh0mt3tcbvelea87.apps.googleusercontent.com",
          "client_type": 3
        }
      ],
      "api_key": [
        {
          "current_key": "AIzaSyDsA6snPQhxtc4LcXYDg3s9-kKxYPE8gmE"
        }
      ],
      "services": {
        "analytics_service": {
          "status": 1
        },
        "appinvite_service": {
          "status": 1,
          "other_platform_oauth_client": []
        },
        "ads_service": {
          "status": 2
        }
      }
    }
  ],
  "configuration_version": "1"
}